Metadata-Version: 1.1
Name: extender
Version: 0.1.0
Summary: extender: A simple plug-in/extension system on Python
Home-page: https://github.com/messense/extender
Author: messense
Author-email: messense@icloud.com
License: MIT License
Keywords: extender,plugin,extension
Platform: UNKNOWN
Classifier: Development Status :: 3 - Alpha
Classifier: Environment :: Plugins
Classifier: License :: OSI Approved :: MIT License
Classifier: Operating System :: MacOS
Classifier: Operating System :: POSIX
Classifier: Operating System :: POSIX :: Linux
Classifier: Programming Language :: Python
Classifier: Programming Language :: Python :: 2.7
Classifier: Programming Language :: Python :: 3.3
Classifier: Programming Language :: Python :: 3.4
